netbox_k8s_cluster_info/__init__.py
netbox_k8s_cluster_info/filtersets.py
netbox_k8s_cluster_info/navigation.py
netbox_k8s_cluster_info/tables.py
netbox_k8s_cluster_info/urls.py
netbox_k8s_cluster_info/api/__init__.py
netbox_k8s_cluster_info/api/serializers.py
netbox_k8s_cluster_info/api/urls.py
netbox_k8s_cluster_info/api/views.py
netbox_k8s_cluster_info/forms/__init__.py
netbox_k8s_cluster_info/forms/k8s_cluster.py
netbox_k8s_cluster_info/forms/k8s_cluster_type.py
netbox_k8s_cluster_info/forms/k8s_service.py
netbox_k8s_cluster_info/migrations/0001_initial.py
netbox_k8s_cluster_info/migrations/__init__.py
netbox_k8s_cluster_info/models/__init__.py
netbox_k8s_cluster_info/models/k8s_cluster.py
netbox_k8s_cluster_info/models/k8s_cluster_type.py
netbox_k8s_cluster_info/models/k8s_service.py
netbox_k8s_cluster_info/templates/netbox_k8s_cluster_info/k8scluster.html
netbox_k8s_cluster_info/templates/netbox_k8s_cluster_info/k8sclustertype.html
netbox_k8s_cluster_info/templates/netbox_k8s_cluster_info/k8sservice.html
netbox_k8s_cluster_info/templates/netbox_k8s_cluster_info/generic/bulk_remove.html
netbox_k8s_cluster_info/templates/netbox_k8s_cluster_info/viewtab_contact/k8scluster_contact.html
netbox_k8s_cluster_info/views/__init__.py
netbox_k8s_cluster_info/views/k8s_cluster.py
netbox_k8s_cluster_info/views/k8s_cluster_type.py
netbox_k8s_cluster_info/views/k8s_service.py
netbox_k8s_cluster_info-1.0.0.dist-info/LICENSE
netbox_k8s_cluster_info-1.0.0.dist-info/METADATA
netbox_k8s_cluster_info-1.0.0.dist-info/WHEEL
netbox_k8s_cluster_info-1.0.0.dist-info/top_level.txt
netbox_k8s_cluster_info-1.0.0.dist-info/RECORD
